AGPLv3.txt
LICENSE.txt
MANIFEST.in
README.rst
babel_gateone.cfg
setup.cfg
setup.py
gateone/__init__.py
gateone.egg-info/PKG-INFO
gateone.egg-info/SOURCES.txt
gateone.egg-info/dependency_links.txt
gateone.egg-info/entry_points.txt
gateone.egg-info/not-zip-safe
gateone.egg-info/requires.txt
gateone.egg-info/top_level.txt
gateone/applications/__init__.py
gateone/applications/example/__init__.py
gateone/applications/example/app_example.py
gateone/applications/example/static/app_example.js
gateone/applications/example/templates/example.css
gateone/applications/example/templates/example.html
gateone/applications/example/templates/settings/50example.conf
gateone/applications/terminal/__init__.py
gateone/applications/terminal/app_terminal.py
gateone/applications/terminal/logviewer.py
gateone/applications/terminal/policy.py
gateone/applications/terminal/term_utils.py
gateone/applications/terminal/woff_info.py
gateone/applications/terminal/docs/app_terminal.rst
gateone/applications/terminal/docs/configuration.rst
gateone/applications/terminal/docs/developer.rst
gateone/applications/terminal/docs/index.rst
gateone/applications/terminal/docs/js_terminal.rst
gateone/applications/terminal/docs/js_terminal_input.rst
gateone/applications/terminal/docs/plugin_bookmarks.rst
gateone/applications/terminal/docs/plugin_convenience.rst
gateone/applications/terminal/docs/plugin_example.rst
gateone/applications/terminal/docs/plugin_logging.rst
gateone/applications/terminal/docs/plugin_notice.rst
gateone/applications/terminal/docs/plugin_playback.rst
gateone/applications/terminal/docs/plugin_ssh.rst
gateone/applications/terminal/docs/userguide.rst
gateone/applications/terminal/docs/woff_info.rst
gateone/applications/terminal/docs/screenshots/gateone_bookmarks_empty.png
gateone/applications/terminal/docs/screenshots/gateone_grid_view.png
gateone/applications/terminal/docs/screenshots/gateone_infopanel.png
gateone/applications/terminal/docs/screenshots/gateone_log_viewer.png
gateone/applications/terminal/docs/screenshots/gateone_login.png
gateone/applications/terminal/docs/screenshots/gateone_login_explained.png
gateone/applications/terminal/docs/screenshots/gateone_new_bookmark1.png
